work_report_tool/__init__.py
work_report_tool/cli.py
work_report_tool/work_report_tool.py
work_report_tool-0.1.0.dist-info/AUTHORS.rst
work_report_tool-0.1.0.dist-info/LICENSE
work_report_tool-0.1.0.dist-info/METADATA
work_report_tool-0.1.0.dist-info/WHEEL
work_report_tool-0.1.0.dist-info/entry_points.txt
work_report_tool-0.1.0.dist-info/top_level.txt
work_report_tool-0.1.0.dist-info/RECORD
