Metadata-Version: 2.1
Name: work-report-tool
Version: 0.1.0
Summary: Tool generating HTML reports based on results fetched from Hubstaff API v1
Home-page: https://github.com/mradecki/work_report_tool
Author: Marek Radecki
Author-email: marek.radecki@gmail.com
License: MIT license
Keywords: work_report_tool
Platform: UNKNOWN
Classifier: Development Status :: 2 - Pre-Alpha
Classifier: Intended Audience :: Developers
Classifier: License :: OSI Approved :: MIT License
Classifier: Natural Language :: English
Classifier: Programming Language :: Python :: 3
Classifier: Programming Language :: Python :: 3.5
Classifier: Programming Language :: Python :: 3.6
Classifier: Programming Language :: Python :: 3.7
Classifier: Programming Language :: Python :: 3.8
Requires-Python: >=3.5
Requires-Dist: Click (>=7.0)
